<Dictionnaire><Dictionnaire><feat att="nom" val="Essai d'un dictionnaire tamaŋ" /><feat att="auteur" val="Benjamin GalliotMartine Mazaudon" /><feat att="commentaire" val="Ça déchire grave !" /><langues><Langue id="tam"><feat att="type_caractères" val="nagari" /><feat att="sens_lecture" val="gauche à droite" /><feat att="autoglossonyme" val="tamaŋ" /><feat att="glossonyme" val="tamaŋ" /><feat att="statuts" val="['source', 'vernaculaire']" /></Langue><Langue id="fra"><feat att="type_caractères" val="latin" /><feat att="sens_lecture" val="gauche à droite" /><feat att="autoglossonyme" val="français" /><feat att="glossonyme" val="français" /><feat att="statuts" val="['cible']" /></Langue><Langue id="eng"><feat att="type_caractères" val="latin" /><feat att="sens_lecture" val="gauche à droite" /><feat att="autoglossonyme" val="English" /><feat att="glossonyme" val="anglais" /><feat att="statuts" val="['cible']" /></Langue><Langue id="nep"><feat att="type_caractères" val="latin" /><feat att="sens_lecture" val="gauche à droite" /><feat att="autoglossonyme" val="nepali" /><feat att="glossonyme" val="népali" /><feat att="statuts" val="['source', 'vernaculaire']" /></Langue><entrées><Entrée id="Ⓔ3aⒽ2"><feat att="vedette" val="3a" /><feat att="homonyme" val="2" /><feat att="classe_grammaticale" val="mod vb" /><définitions><Définition id="Ⓔ3aⒽ2Ⓓ1"><feat att="définition" val="ne ... pas" /><feat att="langue" val="fra" /></Définition><Définition id="Ⓔ3aⒽ2Ⓓ2"><feat att="définition" val="not" /><feat att="langue" val="eng" /></Définition><Définition id="Ⓔ3aⒽ2Ⓓ3"><feat att="définition" val="न" /><feat att="langue" val="tam" /></Définition><Définition id="Ⓔ3aⒽ2Ⓓ4"><feat att="définition" val="na" /><feat att="langue" val="nep" /></Définition></définitions></Entrée><Entrée id="Ⓔ1a-a"><feat att="vedette" val="1a-a" /><feat att="classe_grammaticale" val="interj" /><définitions><Définition id="Ⓔ1a-aⒹ1"><feat att="définition" val="non!" /><feat att="langue" val="fra" /></Définition><Définition id="Ⓔ1a-aⒹ2"><feat att="définition" val="no!" /><feat att="langue" val="eng" /></Définition><Définition id="Ⓔ1a-aⒹ3"><feat att="définition" val="अहँ" /><feat att="langue" val="tam" /></Définition><Définition id="Ⓔ1a-aⒹ4"><feat att="définition" val="aham̐" /><feat att="langue" val="nep" /></Définition></définitions></Entrée><Entrée id="Ⓔ2ai"><feat att="vedette" val="2ai" /><feat att="classe_grammaticale" val="pron" /><définitions><Définition id="Ⓔ2aiⒹ1"><feat att="définition" val="tu, toi" /><feat att="langue" val="fra" /></Définition><Définition id="Ⓔ2aiⒹ2"><feat att="définition" val="you (sg)" /><feat att="langue" val="eng" /></Définition><Définition id="Ⓔ2aiⒹ3"><feat att="définition" val="तिमी, तपाईं" /><feat att="langue" val="tam" /></Définition><Définition id="Ⓔ2aiⒹ4"><feat att="définition" val="timī, tapāīm̐" /><feat att="langue" val="nep" /></Définition></définitions></Entrée><Entrée id="Ⓔ2ai-ni"><feat att="vedette" val="2ai-ni" /><feat att="classe_grammaticale" val="pron" /><définitions><Définition id="Ⓔ2ai-niⒹ1"><feat att="définition" val="vous (pl)" /><feat att="langue" val="fra" /></Définition><Définition id="Ⓔ2ai-niⒹ2"><feat att="définition" val="you (pl)" /><feat att="langue" val="eng" /></Définition><Définition id="Ⓔ2ai-niⒹ3"><feat att="définition" val="तपाईंहरू" /><feat att="langue" val="tam" /></Définition><Définition id="Ⓔ2ai-niⒹ4"><feat att="définition" val="tapāīm̐haru" /><feat att="langue" val="nep" /></Définition></définitions></Entrée><Entrée id="Ⓔ2airak"><feat att="vedette" val="2airak" /><feat att="classe_grammaticale" val="n" /><définitions><Définition id="Ⓔ2airakⒹ1"><feat att="définition" val="alcool" /><feat att="langue" val="fra" /></Définition><Définition id="Ⓔ2airakⒹ2"><feat att="définition" val="spirit, alcohol" /><feat att="langue" val="eng" /></Définition><Définition id="Ⓔ2airakⒹ3"><feat att="définition" val="रक्सी" /><feat att="langue" val="tam" /></Définition><Définition id="Ⓔ2airakⒹ4"><feat att="définition" val="raksī" /><feat att="langue" val="nep" /></Définition></définitions></Entrée><Entrée id="Ⓔ2auti"><feat att="vedette" val="2auti" /><feat att="classe_grammaticale" val="n, adv" /><définitions><Définition id="Ⓔ2autiⒹ1"><feat att="définition" val="chose extraordinaire ou excessive" /><feat att="langue" val="fra" /></Définition><Définition id="Ⓔ2autiⒹ2"><feat att="définition" val="extraordinary thing or event, excess" /><feat att="langue" val="eng" /></Définition><Définition id="Ⓔ2autiⒹ3"><feat att="définition" val="अति, अचम्म, असाधारण" /><feat att="langue" val="tam" /></Définition><Définition id="Ⓔ2autiⒹ4"><feat att="définition" val="ati, acamma, asādhāran̩" /><feat att="langue" val="nep" /></Définition></définitions></Entrée><Entrée id="Ⓔ1aku"><feat att="vedette" val="1aku" /><feat att="classe_grammaticale" val="n" /><sens><Sens id="Ⓔ1akuⓈ1"><feat att="acception" val="1" /><définitions><Définition id="Ⓔ1akuⓈ1Ⓓ1"><feat att="définition" val="oncle: frère cadet du père" /><feat att="langue" val="fra" /></Définition><Définition id="Ⓔ1akuⓈ1Ⓓ2"><feat att="définition" val="uncle: father's younger brother" /><feat att="langue" val="eng" /></Définition><Définition id="Ⓔ1akuⓈ1Ⓓ3"><feat att="définition" val="काका" /><feat att="langue" val="tam" /></Définition><Définition id="Ⓔ1akuⓈ1Ⓓ4"><feat att="définition" val="kākā" /><feat att="langue" val="nep" /></Définition></définitions></Sens><Sens id="Ⓔ1akuⓈ2"><feat att="acception" val="2" /><définitions><Définition id="Ⓔ1akuⓈ2Ⓓ1"><feat att="définition" val="mari de la soeur cadette de la mère (\lang{2aru})" /><feat att="langue" val="fra" /></Définition><Définition id="Ⓔ1akuⓈ2Ⓓ2"><feat att="définition" val="mother's younger sister's husband" /><feat att="langue" val="eng" /></Définition><Définition id="Ⓔ1akuⓈ2Ⓓ3"><feat att="définition" val="सानु बाउ" /><feat att="langue" val="tam" /></Définition><Définition id="Ⓔ1akuⓈ2Ⓓ4"><feat att="définition" val="sānu bāu" /><feat att="langue" val="nep" /></Définition></définitions></Sens></sens></Entrée></entrées></langues></Dictionnaire></Dictionnaire>